hive/__init__.py
hive/cli.py
hive/parsers.py
hive/spinner.py
hive_cli-0.2.2.dist-info/entry_points.txt
hive_cli-0.2.2.dist-info/LICENSE
hive_cli-0.2.2.dist-info/WHEEL
hive_cli-0.2.2.dist-info/METADATA
hive_cli-0.2.2.dist-info/RECORD
