Metadata-Version: 2.1
Name: hive-cli
Version: 0.2.2
Summary: 
Author: paul
Author-email: ppierzc@gmail.copm
Requires-Python: >=3.9,<3.12
Classifier: Programming Language :: Python :: 3
Classifier: Programming Language :: Python :: 3.9
Classifier: Programming Language :: Python :: 3.10
Requires-Dist: Pillow (>=9.5.0,<10.0.0)
Requires-Dist: PyPDF2 (>=3.0.1,<4.0.0)
Requires-Dist: qdrant-client (>=1.1.7,<2.0.0)
Requires-Dist: sentence-transformers (>=2.2.2,<3.0.0)
Requires-Dist: torch (>=2.0.1,<3.0.0)
Requires-Dist: typer[all] (>=0.9.0,<0.10.0)
